setup.py
test/__init__.py
test/tokens_test.py
wire4_auth/__init__.py
wire4_auth.egg-info/PKG-INFO
wire4_auth.egg-info/SOURCES.txt
wire4_auth.egg-info/dependency_links.txt
wire4_auth.egg-info/requires.txt
wire4_auth.egg-info/top_level.txt
wire4_auth/auth/__init__.py
wire4_auth/auth/oauth_wire4.py
wire4_auth/core/__init__.py
wire4_auth/core/cached_token.py
wire4_auth/core/environment_enum.py
wire4_auth/webhook_verification_signature/__init__.py
wire4_auth/webhook_verification_signature/utils_compute.py
wire4_auth_p27/__init__.py
wire4_auth_p27/auth/__init__.py
wire4_auth_p27/auth/oauth_wire4.py
wire4_auth_p27/core/__init__.py
wire4_auth_p27/core/cached_token.py
wire4_auth_p27/core/environment_enum.py
wire4_auth_p27/webhook_verification_signature/__init__.py
wire4_auth_p27/webhook_verification_signature/utils_compute.py