Metadata-Version: 1.0
Name: wire4-auth
Version: 1.1.1
Summary: Wire4Authenticator
Home-page: http://wire4.mx
Author: Wire4
Author-email: speiok-team@tcpip.tech
License: UNKNOWN
Keywords: Swagger,Wire4Authenticator
Platform: UNKNOWN
